or2.v
module or2(y,a,b);
output y;

input a,b;

assign y = a | b;

endmodule

or2_tb.v
//or2_tb.v
`timescale 10ms / 1ms
`include "or2.v"

module or2_tb();

reg a,b;
wire y;
or2 gate(y,a,b);

initial begin
    $dumpfile("or2.vcd");
    $dumpvars(0, or2_tb);
    #10 a=0; b=0;
    #100;
    $finish;
end

always #10 a = ~a;

always #5 b = ~b;

endmodule

or2.vcd
$date
	Sun Jun  7 18:07:51 2020
$end
$version
	Icarus Verilog
$end
$timescale
	1ms
$end
$scope module or2_tb $end
$var wire 1 ! y $end
$var reg 1 " a $end
$var reg 1 # b $end
$scope module gate $end
$var wire 1 " a $end
$var wire 1 # b $end
$var wire 1 ! y $end
$upscope $end
$upscope $end
$enddefinitions $end
#0
$dumpvars
x#
x"
x!
$end
#100
1!
1#
1"
#150
0#
#200
1#
0"
#250
0!
0#
#300
1!
1#
1"
#350
0#
#400
1#
0"
#450
0!
0#
#500
1!
1#
1"
#550
0#
#600
1#
0"
#650
0!
0#
#700
1!
1#
1"
#750
0#
#800
1#
0"
#850
0!
0#
#900
1!
1#
1"
#950
0#
#1000
1#
0"
#1050
0!
0#
#1100
1!
1#
1"
