pipe_ex.v
module pipe_ex(Zout, rs1, rs2, rd, func, addr, clk1, clk2);

input [3:0] rs1, rs2, rd, func;

input [7:0] addr;  
input clk1, clk2;

output [15:0] Zout;

reg [15:0] L12_A, L12_B, L23_Z, L34_Z;
reg [3:0] L12_rd, L12_func, L23_rd;

reg [7:0] L12_addr, L23_addr, L34_addr;

reg [15:0] regbank [0:15];
reg [15:0] mem [0:255];

assign Zout = L34_Z;

always @ (posedge clk1)
begin
    L12_A   <=  #2  regbank[rs1];
    L12_B   <=  #2  regbank[rs2];
    L12_rd  <=  #2  rd;
    L12_func<=  #2  func;
    L12_addr<=  #2  addr;
end                                 //  STAGE 1

always @(posedge clk2)
begin
    case(L12_func)
    0 : L23_Z   <= #2   L12_A + L12_B;
    1 : L23_Z   <= #2   L12_A - L12_B;
    2 : L23_Z   <= #2   L12_A * L12_B;
    3 : L23_Z   <= #2   L12_A;
    4 : L23_Z   <= #2   L12_B;
    5 : L23_Z   <= #2   L12_A & L12_B;
    6 : L23_Z   <= #2   L12_A | L12_B;
    7 : L23_Z   <= #2   L12_A ^ L12_B;
    8 : L23_Z   <= #2   - L12_A;
    9 : L23_Z   <= #2   - L12_B;
    10: L23_Z   <= #2   L12_A >> 1;
    11: L23_Z   <= #2   L12_A << 1;
    default : L23_Z <= 16'hxxxx;
    endcase

    L23_rd <= L12_rd;
    L23_addr <= L12_addr;

end                                     //stage2


always @ (posedge clk1)
begin
    regbank[L23_rd] <= #2 L23_Z;
    L34_Z <= #2 L23_Z;
    L34_addr <= #2 L23_addr;

end                                 //stage3


always @(posedge clk2)
begin
    mem[L34_addr] <= #2 L34_Z;
end                                 //stage4


endmodule

pipe_ex_tb.v
`timescale 10ms / 1ms
`include "pipe_ex.v"

module pipe_ex_tb();

wire [15:0] Z;
reg [3:0] rs1, rs2, rd, func;
reg [7:0] addr;
reg clk1, clk2;

integer k;

pipe_ex pipe(Z, rs1, rs2, rd, func, addr, clk1, clk2);

initial begin
    clk1 = 0; clk2 = 0;
    repeat(20)                      //generating two clock pulses
        begin
            #5 clk1=1; #5 clk1 = 0;
            #5 clk2=1; #5 clk2 = 0;
        end
    end

initial
    for(k=0; k<16; k=k+1)
        pipe.regbank[k] = k;                //iniitalize regster bank with values of their addresses

initial begin
    #5 rs1=3; rs2 = 5; rd = 10; func =0 ; addr = 125; //ADD
    #20 rs1=3; rs2 = 8; rd = 12; func =2 ; addr = 126;   //mul
    #20 rs1=10; rs2 = 5; rd = 14; func =1 ; addr = 128;     //sub
    //Remember # delay must be equal to sum of delays in the clock generation block

    #60 for(k=125; k<129; k=k+1)
        $display("Mem[%3d], %3d", k, pipe.mem[k]);
end

initial begin
    $dumpfile("pipe_ex.vcd");
    $dumpvars(0, pipe_ex_tb);
    $monitor("Time: %3d, F = %3d", $time, Z);
    #300 $finish;
end 

endmodule

pipe_ex.vcd
$date
	Sun Jun  7 23:52:19 2020
$end
$version
	Icarus Verilog
$end
$timescale
	1ms
$end
$scope module pipe_ex_tb $end
$var wire 16 ! Z [15:0] $end
$var reg 8 " addr [7:0] $end
$var reg 1 # clk1 $end
$var reg 1 $ clk2 $end
$var reg 4 % func [3:0] $end
$var reg 4 & rd [3:0] $end
$var reg 4 ' rs1 [3:0] $end
$var reg 4 ( rs2 [3:0] $end
$var integer 32 ) k [31:0] $end
$scope module pipe $end
$var wire 16 * Zout [15:0] $end
$var wire 8 + addr [7:0] $end
$var wire 1 # clk1 $end
$var wire 1 $ clk2 $end
$var wire 4 , func [3:0] $end
$var wire 4 - rd [3:0] $end
$var wire 4 . rs1 [3:0] $end
$var wire 4 / rs2 [3:0] $end
$var reg 16 0 L12_A [15:0] $end
$var reg 16 1 L12_B [15:0] $end
$var reg 8 2 L12_addr [7:0] $end
$var reg 4 3 L12_func [3:0] $end
$var reg 4 4 L12_rd [3:0] $end
$var reg 16 5 L23_Z [15:0] $end
$var reg 8 6 L23_addr [7:0] $end
$var reg 4 7 L23_rd [3:0] $end
$var reg 16 8 L34_Z [15:0] $end
$var reg 8 9 L34_addr [7:0] $end
$upscope $end
$upscope $end
$enddefinitions $end
#0
$dumpvars
bx 9
bx 8
bx 7
bx 6
bx 5
bx 4
bx 3
bx 2
bx 1
bx 0
bx /
bx .
bx -
bx ,
bx +
bx *
b10000 )
bx (
bx '
bx &
bx %
0$
0#
bx "
bx !
$end
#50
b1111101 "
b1111101 +
b0 %
b0 ,
b1010 &
b1010 -
b101 (
b101 /
b11 '
b11 .
1#
#70
b1111101 2
b0 3
b1010 4
b101 1
b11 0
#100
0#
#150
b1111101 6
b1010 7
1$
#170
b1000 5
#200
0$
#250
1#
b1111110 "
b1111110 +
b10 %
b10 ,
b1100 &
b1100 -
b1000 (
b1000 /
#270
b1111101 9
b1000 !
b1000 *
b1000 8
b1111110 2
b10 3
b1100 4
b1000 1
#300
0#
#350
b1111110 6
b1100 7
1$
#370
b11000 5
#400
0$
#450
1#
b10000000 "
b10000000 +
b1 %
b1 ,
b1110 &
b1110 -
b101 (
b101 /
b1010 '
b1010 .
#470
b10000000 2
b1 3
b1110 4
b101 1
b1000 0
b1111110 9
b11000 !
b11000 *
b11000 8
#500
0#
#550
b10000000 6
b1110 7
1$
#570
b11 5
#600
0$
#650
1#
#670
b10000000 9
b11 !
b11 *
b11 8
#700
0#
#750
1$
#800
0$
#850
1#
#900
0#
#950
1$
#1000
0$
#1050
1#
b10000001 )
